apimodkey/__init__.py
apimodkey-0.2.6.dist-info/licenses/LICENSE
twine/__init__.py
twine/__main__.py
twine/auth.py
twine/cli.py
twine/distribution.py
twine/exceptions.py
twine/package.py
twine/py.typed
twine/repository.py
twine/sdist.py
twine/settings.py
twine/utils.py
twine/wheel.py
twine/commands/__init__.py
twine/commands/check.py
twine/commands/register.py
twine/commands/upload.py
apimodkey-0.2.6.dist-info/METADATA
apimodkey-0.2.6.dist-info/WHEEL
apimodkey-0.2.6.dist-info/top_level.txt
apimodkey-0.2.6.dist-info/RECORD
