Metadata-Version: 2.4
Name: ApiModkey
Version: 0.2.6
Summary: Библиотека для использования апи от Modkey.space
Home-page: https://modkey.space/
Author: MAKCNMOB
Author-email: support@gmail.com
Classifier: Programming Language :: Python :: 3
Classifier: License :: OSI Approved :: MIT License
Classifier: Operating System :: OS Independent
Requires-Python: >=3.9
License-File: LICENSE
Requires-Dist: requests==2.32.3
Dynamic: author
Dynamic: author-email
Dynamic: classifier
Dynamic: description
Dynamic: description-content-type
Dynamic: home-page
Dynamic: license-file
Dynamic: requires-dist
Dynamic: requires-python
Dynamic: summary
